docs/source/conf.py
gamut/__init__.py
gamut/__main__.py
gamut/__version__.py
gamut/audio.py
gamut/config.py
gamut/controls.py
gamut/data.py
gamut/features.py
gamut/sys.py
gamut/utils.py
gamut/gui/__gui_init__.py
gamut/gui/__init__.py
gamut/gui/audio.py
gamut/gui/buttons.py
gamut/gui/config.py
gamut/gui/corpus.py
gamut/gui/dialogs.py
gamut/gui/mosaic.py
gamut/gui/theme.py
gamut/gui/utils.py
gamut/gui/data/audio/silence.mp3
gamut/gui/data/images/icon.png
gamut/gui/data/images/logo.png
gamut/gui/data/widgets/audio.kv
gamut/gui/data/widgets/corpus.kv
gamut/gui/data/widgets/dialogs.kv
gamut/gui/data/widgets/main.kv
gamut/gui/data/widgets/mosaic.kv
gamut/gui/data/widgets/param.kv
gamut/gui/data/widgets/widgets.kv
tests/main.py
gamut-1.2.1.dist-info/LICENSE
gamut-1.2.1.dist-info/METADATA
gamut-1.2.1.dist-info/WHEEL
gamut-1.2.1.dist-info/entry_points.txt
gamut-1.2.1.dist-info/top_level.txt
gamut-1.2.1.dist-info/RECORD
