Metadata-Version: 2.1
Name: gamut
Version: 1.2.1
Summary: Granular Audio Musaicing Toolkit for Python
Author-email: Felipe Tovar-Henao <felipe.tovar.henao@gmail.com>
License: OSI Approved :: ISC License (ISCL)
Keywords: DSP,audio musaicking,granulation,machine learning,ML,MIR,music,sound design,concatenative synthesis
Classifier: Development Status :: 5 - Production/Stable
Classifier: Intended Audience :: Other Audience
Classifier: Natural Language :: English
Classifier: Operating System :: MacOS :: MacOS X
Classifier: Operating System :: Microsoft :: Windows
Classifier: Programming Language :: Python
Requires-Python: >=3.7
License-File: LICENSE
Requires-Dist: numpy
Requires-Dist: librosa
Requires-Dist: matplotlib
Requires-Dist: progress ~=1.6
Requires-Dist: scipy
Requires-Dist: SoundFile
Requires-Dist: sounddevice
Requires-Dist: typing-extensions
Requires-Dist: filetype
Requires-Dist: kivy[base]
Requires-Dist: Sphinx
Requires-Dist: sphinx-copybutton
Requires-Dist: sphinx-rtd-theme
